{
    "stac_version": "1.0.0",
    "type": "Collection",
    "stac_extensions": [
        "https://stac-extensions.github.io/eo/v1.0.0/schema.json"
    ],
    "id": "projects/earthengine-legacy/assets/projects/sat-io/open-datasets/global_wind_atlas/capacity-factor",
    "title": "Global Wind Atlas: Capacity Factor",
    "description": "Global Wind Atlas: Capacity Factor",
    "license": "CC-BY-4.0",
    "gee:type": "image_collection",
    "links": [
        {
            "rel": "self",
            "href": "https://raw.githubusercontent.com/samapriya/awesome-gee-community-datasets/master/catalog/global_wind_atlas_capacity-factor.json",
            "type": "application/json"
        },
        {
            "rel": "parent",
            "href": "https://raw.githubusercontent.com/samapriya/awesome-gee-community-datasets/master/catalog/stac_catalog.json",
            "type": "application/json"
        },
        {
            "rel": "root",
            "href": "https://raw.githubusercontent.com/samapriya/awesome-gee-community-datasets/master/catalog/stac_catalog.json",
            "type": "application/json"
        },
        {
            "title": "Run the example for Global Wind Atlas: Capacity Factor in the Google Playground",
            "rel": "related",
            "href": "https://code.earthengine.google.com/8c3d27d67a2e7d9bda015c325d505409",
            "type": "text/html",
            "code": "JavaScript"
        },
        {
            "rel": "license",
            "href": "https://raw.githubusercontent.com/samapriya/awesome-gee-community-datasets/master/LICENSE"
        }
    ],
    "extent": {
        "spatial": {
            "bbox": [
                [
                    -180,
                    -90,
                    180,
                    90
                ]
            ]
        },
        "temporal": {
            "interval": [
                [
                    "2021-07-11T07:47:07.422017Z",
                    "2021-07-11T07:47:07.422017Z"
                ]
            ]
        }
    },
    "gee:terms_of_use": "This dataset is made available publicly under CC-BY-4.0.",
    "gee:user_uploaded": true,
    "keywords": [
        "Wind, energy, ruggedness index, capacity factor, wind speed, power density"
    ],
    "providers": [
        {
            "name": "Global Wind Atlas, Department of Wind Energy at the Technical University of Denmark (DTU Wind Energy) and the World Bank Group (consisting of The World Bank and the International Finance Corporation, or IFC)",
            "roles": [
                "producer",
                "licensor"
            ]
        },
        {
            "name": "Samapriya Roy",
            "roles": [
                "processor"
            ]
        }
    ],
    "eo:bands": [
        {
            "name": "b1",
            "gsd": 278,
            "min": 0.0,
            "max": 0.92,
            "gee:estimated_range": true
        }
    ],
    "eo:properties": {
        "all_users_can_read": true,
        "hub_height": "100",
        "num_bands": "1",
        "rotor_diameters": "112,126,136"
    }
}