{
    "stac_version": "1.0.0",
    "type": "Collection",
    "stac_extensions": [
        "https://stac-extensions.github.io/eo/v1.0.0/schema.json"
    ],
    "id": "projects/sat-io/open-datasets/landfire/topographic/elevation",
    "title": "Elevation (ELEV) LF v2.0.0",
    "description": "Elevation (ELEV) LF v2.0.0",
    "license": "PDDL-1.0",
    "gee:type": "image_collection",
    "links": [
        {
            "rel": "self",
            "href": "https://raw.githubusercontent.com/samapriya/awesome-gee-community-datasets/master/catalog/open-datasets_landfire_topographic_elevation.json",
            "type": "application/json"
        },
        {
            "rel": "parent",
            "href": "https://raw.githubusercontent.com/samapriya/awesome-gee-community-datasets/master/catalog/stac_catalog.json",
            "type": "application/json"
        },
        {
            "rel": "root",
            "href": "https://raw.githubusercontent.com/samapriya/awesome-gee-community-datasets/master/catalog/stac_catalog.json",
            "type": "application/json"
        },
        {
            "title": "Run the example for Elevation (ELEV) LF v2.0.0 in the Google Playground",
            "rel": "related",
            "href": "https://code.earthengine.google.com/b162248aa8a2495648f10baed01e7ef3",
            "type": "text/html",
            "code": "JavaScript"
        },
        {
            "rel": "license",
            "href": "https://raw.githubusercontent.com/samapriya/awesome-gee-community-datasets/master/LICENSE"
        }
    ],
    "extent": {
        "spatial": {
            "bbox": [
                [
                    -160.6051534144912,
                    18.839791601174092,
                    -65.06142229925803,
                    51.69884308652948
                ]
            ]
        },
        "temporal": {
            "interval": [
                [
                    "2021-04-19T00:58:49.756291Z",
                    "2021-04-19T00:58:49.756291Z"
                ]
            ]
        }
    },
    "gee:terms_of_use": "This dataset is made available publicly under PDDL-1.0.",
    "gee:user_uploaded": true,
    "keywords": [
        "doi, fire, landfire, nature-conservancy, usda, usgs, vegetation, wildfire"
    ],
    "providers": [
        {
            "name": "U.S. Department of Agriculture's (USDA) U.S. Forest Service (USFS), U.S. Department of the Interior's Geological Survey (USGS), and The Nature Conservancy",
            "roles": [
                "producer",
                "licensor"
            ]
        },
        {
            "name": "Samapriya Roy",
            "roles": [
                "processor"
            ]
        }
    ],
    "eo:bands": [
        {
            "name": "b1",
            "gsd": 30,
            "min": -85,
            "max": 32767,
            "gee:estimated_range": true
        }
    ],
    "eo:properties": {
        "all_users_can_read": true,
        "num_bands": "1"
    }
}