{
    "stac_version": "1.0.0",
    "type": "Collection",
    "stac_extensions": [
        "https://stac-extensions.github.io/eo/v1.0.0/schema.json"
    ],
    "id": "projects/sat-io/open-datasets/NOAA/conus_ccap_wetland_potential",
    "title": "C-CAP Wetland Potential 30m",
    "description": "C-CAP Wetland Potential 30m",
    "license": "CC-BY-4.0",
    "gee:type": "image",
    "links": [
        {
            "rel": "self",
            "href": "https://raw.githubusercontent.com/samapriya/awesome-gee-community-datasets/master/catalog/open-datasets_NOAA_conus_ccap_wetland_potential.json",
            "type": "application/json"
        },
        {
            "rel": "parent",
            "href": "https://raw.githubusercontent.com/samapriya/awesome-gee-community-datasets/master/catalog/stac_catalog.json",
            "type": "application/json"
        },
        {
            "rel": "root",
            "href": "https://raw.githubusercontent.com/samapriya/awesome-gee-community-datasets/master/catalog/stac_catalog.json",
            "type": "application/json"
        },
        {
            "title": "Run the example for C-CAP Wetland Potential 30m in the Google Playground",
            "rel": "related",
            "href": "https://code.earthengine.google.com/?scriptPath=users/sat-io/awesome-gee-catalog-examples:regional-landuse-landcover/CCAP-WETLAND-POTENTIAL",
            "type": "text/html",
            "code": "JavaScript"
        },
        {
            "rel": "license",
            "href": "https://spdx.org/licenses/CC-BY-4.0.html",
            "type": "text/html"
        }
    ],
    "extent": {
        "spatial": {
            "bbox": [
                [
                    -127.98187617930571,
                    22.768461673936308,
                    -65.2773517208073,
                    51.69806074897534
                ]
            ]
        },
        "temporal": {
            "interval": [
                [
                    "2022-05-17T15:05:24.284192Z",
                    "2020-10-29T00:00:00Z"
                ]
            ]
        }
    },
    "gee:terms_of_use": "This dataset is made available publicly under CC-BY-4.0.",
    "gee:user_uploaded": true,
    "keywords": [
        "Wetland",
        "Coastal data",
        "NOAA",
        "Remote Sensing"
    ],
    "providers": [
        {
            "name": "NOAA's Ocean Service, Office for Coastal Management (OCM)",
            "roles": [
                "producer",
                "licensor"
            ]
        },
        {
            "name": "Samapriya Roy",
            "roles": [
                "processor"
            ]
        }
    ],
    "eo:bands": [
        {
            "name": "b1",
            "gsd": 30,
            "min": 0,
            "max": 10,
            "gee:estimated_range": true
        }
    ],
    "eo:properties": {
        "all_users_can_read": true
    }
}